cratex/__init__.py
cratex/run.bat
cratex/jdevtools/__init__.py
cratex/jdevtools/jCLI.py
cratex/jdevtools/jgui.py
cratex/jdevtools/jweb.py
cratex/jdevtools/bots/__init__.py
cratex/jdevtools/data/__init__.py
cratex/jdevtools/extras/__init__.py
cratex/jdevtools/models/__init__.py
cratex/jdevtools/models/jkanda.py
cratex/jdevtools/models/jkissalu.py
cratex/jdevtools/models/jmesso.py
cratex/jdevtools/servers/__init__.py
cratex-0.123.0.dist-info/LICENSE
cratex-0.123.0.dist-info/WHEEL
cratex-0.123.0.dist-info/METADATA
cratex-0.123.0.dist-info/RECORD
