Metadata-Version: 2.1
Name: cratex
Version: 0.123.0
Summary: 👨‍💻🛠️🔥⌛🏃📦Python bindings for the Qt cross platform application 
Author: Yackadan V. dsfm
Author-email: yvanoack@eu.zz
Classifier: License :: OSI Approved :: GNU General Public License v3 or later (GPLv3+)
Classifier: Programming Language :: Python :: 2
Classifier: Programming Language :: Python :: 3
Classifier: License :: OSI Approved :: GNU General Public License v3 (GPLv3)
